{
  "wooden_boxes": [
    {
      "url": "images/img1.jpg",
      "name": "ROSE ON GRASS",
      "id": 1,
      "description": "Lorem ipsum dolor sit amet, consectetur adipiscing elit, sed do eiusmod tempor incididunt ut labore et dolore magna aliqua.",
      "date": 1422153200637
    },
    {
      "url": "images/img2.jpg",
      "name": "DARK ROSE",
      "id": 2,
      "description": "Lorem ipsum dolor sit amet",
      "date": 1421153200637
    },
    {
      "url": "images/img3.jpg",
      "name": "WHITE CHRISANTEMA",
      "id": 3,
      "description": "Lorem ipsum dolor sit amet, consectetur adipiscing elit, sed do eiusmod tempor incididunt ut labore et dolore magna aliqua.",
      "date": 1426153200637
    },
    {
      "url": "images/img4.jpg",
      "name": "OPEN ROSE",
      "id": 4,
      "description": "Lorem ipsum dolor sit amet, consectetur adipiscing elit, sed do eiusmod tempor incididunt ut labore et dolore magna aliqua.",
      "date": 1428153200637
    },
    {
      "url": "images/img5.jpg",
      "name": "ROSE AND MIRROR",
      "id": 5,
      "description": "Lorem ipsum dolor sit amet, consectetur adipiscing elit, sed do eiusmod tempor incididunt ut labore et dolore magna aliqua.",
      "date": 1402153200637
    },
    {
      "url": "images/img6.jpg",
      "name": "MAGNOLIA",
      "description": "Lorem ipsum dolor sit amet, consectetur adipiscing elit, sed do eiusmod tempor incididunt ut labore et dolore magna aliqua.",
      "id": 6,
      "date": 1482153200611
    },
    {
      "url": "images/img7.jpg",
      "name": "ORCHIDS AND ROSE",
      "id": 7,
      "description": "Lorem ipsum dolor sit amet, consectetur adipiscing elit, sed do eiusmod tempor incididunt ut labore et dolore magna aliqua.",
      "date": 1482153200637
    },
    {
      "url": "images/img8.jpg",
      "name": "Big Orchid",
      "id": 8,
      "description": "Lorem ipsum dolor sit amet, consectetur adipiscing elit, sed do eiusmod tempor incididunt ut labore et dolore magna aliqua.",
      "date": 1442153200637
    },
    {
      "url": "images/img9.jpg",
      "name":"Rose and buds",
      "id": 9,
      "description": "Lorem ipsum dolor sit amet",
      "date": 1322153200637
    },
    {
      "url": "images/img10.jpg",
      "name": "Big CHRISANTEMA",
      "id": 10,
      "description": "Lorem ipsum dolor sit amet",
      "date": 1322159200637
    }
  ],
  "user": {
    "login": "levon@levon.levon",
    "password": "levon5"
  }
}